README.rst
setup.py
sqlite3_api/Table.py
sqlite3_api/__init__.py
sqlite3_api/api.py
sqlite3_api/field_types.py
sqlite3_api/main.py
sqlite3_api.egg-info/PKG-INFO
sqlite3_api.egg-info/SOURCES.txt
sqlite3_api.egg-info/dependency_links.txt
sqlite3_api.egg-info/top_level.txt