Metadata-Version: 1.1
Name: sqlite3-api
Version: 2.0.2
Summary: API for sqlite3
Home-page: https://github.com/AlexDev-py/sqlite3-api.git
Author: AlexDev
Author-email: aleks.filiov@yandex.ru
License: MIT
Platform: UNKNOWN
Classifier: License :: OSI Approved :: MIT License
Classifier: Programming Language :: Python :: 3.8
